<?xml version="1.0" encoding="UTF-8"?>

<entity-engine-xml>

    <Party partyId="C01" partyTypeId="PARTY_GROUP"/>
    <PartyGroup partyId="C01" groupName="HotWax System 01"/>
    <PartyRole partyId="C01" roleTypeId="PARENT_ORGANIZATION"/>
    <PartyRole partyId="C01" roleTypeId="INTERNAL_ORGANIZATIO"/>

    <Party partyId="C02" partyTypeId="PARTY_GROUP"/>
    <PartyGroup partyId="C02" groupName="HotWax System 02"/>
    <PartyRole partyId="C02" roleTypeId="PARENT_ORGANIZATION"/>
    <PartyRole partyId="C02" roleTypeId="INTERNAL_ORGANIZATIO"/>

    <Party partyId="C03" partyTypeId="PARTY_GROUP"/>
    <PartyGroup partyId="C03" groupName="HotWax System 03"/>
    <PartyRole partyId="C03" roleTypeId="PARENT_ORGANIZATION"/>
    <PartyRole partyId="C03" roleTypeId="INTERNAL_ORGANIZATIO"/>

</entity-engine-xml>